OpenOrchestratorConnection/__init__.py
OpenOrchestratorConnection/crypto_util.py
OpenOrchestratorConnection/db_util.py
OpenOrchestratorConnection/orchestrator_connection.py
OpenOrchestratorConnection-0.0.10.dist-info/LICENSE
OpenOrchestratorConnection-0.0.10.dist-info/METADATA
OpenOrchestratorConnection-0.0.10.dist-info/WHEEL
OpenOrchestratorConnection-0.0.10.dist-info/top_level.txt
OpenOrchestratorConnection-0.0.10.dist-info/RECORD
