Metadata-Version: 2.1
Name: OpenOrchestratorConnection
Version: 0.0.10
Summary: Connection library to use with the OpenOrchestrator project
Author-email: ITK Development <itk-rpa@mkb.aarhus.dk>
Project-URL: Homepage, https://github.com/itk-dev-rpa/OpenOrchestratorConnection
Project-URL: Bug Tracker, https://github.com/itk-dev-rpa/OpenOrchestratorConnection/issues
Classifier: Programming Language :: Python :: 3
Classifier: License :: OSI Approved :: MIT License
Classifier: Operating System :: Microsoft :: Windows
Requires-Python: >=3.7
License-File: LICENSE
Requires-Dist: pyodbc >=4.0.39
Requires-Dist: cryptography >=41.0.3
Requires-Dist: PyPika >=0.48.9
